crec/__init__.py
crec/cli.py
crec/main.py
crec/sources/__init__.py
crec/sources/generic.py
crec/sources/handler.py
crec/sources/instagram.py
crec/sources/tiktok.py
crec/sources/twitter.py
crec/sources/youtube.py
crec/utils/__init__.py
crec/utils/file_handler.py
crec/utils/notify.py
crec/utils/progress.py
crec/utils/quality.py
crec/utils/version.py
crec-1.0.2.dist-info/licenses/LICENSE
crec-1.0.2.dist-info/METADATA
crec-1.0.2.dist-info/WHEEL
crec-1.0.2.dist-info/entry_points.txt
crec-1.0.2.dist-info/top_level.txt
crec-1.0.2.dist-info/RECORD
