Metadata-Version: 2.4
Name: crec
Version: 1.0.2
Summary: A command-line tool for downloading videos from various platforms
Home-page: https://github.com/knkr1/crec
Author: knkr1
Author-email: Karesi <kaan@karesi.dev>
License: MIT
Project-URL: Homepage, https://github.com/knkr1/crec
Project-URL: Repository, https://github.com/knkr1/crec.git
Requires-Python: >=3.7
License-File: LICENSE
Requires-Dist: yt-dlp
Requires-Dist: ffmpeg-python
Dynamic: author
Dynamic: home-page
Dynamic: license-file
Dynamic: requires-python
